tests/__init__.py
tests/aitertools.py
tests/config.py
tests/harness.py
tests/helper.py
tests/responses.py
tests/internet/__init__.py
tests/internet/http_test.py
tests/main/__init__.py
tests/main/client/__init__.py
tests/main/client/account_http_test.py
tests/main/client/blockchain_http_test.py
tests/main/client/config_http_test.py
tests/main/client/http_test.py
tests/main/client/listener_test.py
tests/main/client/metadata_http_test.py
tests/main/client/mosaic_http_test.py
tests/main/client/namespace_http_test.py
tests/main/client/network_http_test.py
tests/main/client/node_http_test.py
tests/main/client/transaction_http_test.py
tests/main/models/__init__.py
tests/main/models/account_test.py
tests/main/models/blockchain_test.py
tests/main/models/mosaic_test.py
tests/main/models/namespace_test.py
tests/main/models/recipient_test.py
tests/main/models/transaction_test.py
tests/main/util/__init__.py
tests/main/util/asynchronous_test.py
tests/main/util/base64_test.py
tests/main/util/binascii_test.py
tests/main/util/bit_test.py
tests/main/util/dataclass_test.py
tests/main/util/identifier_test.py
tests/main/util/mixin_test.py
tests/main/util/observable_test.py
tests/main/util/stdint_test.py
tests/main/util/hashlib/__init__.py
tests/main/util/hashlib/helper.py
tests/main/util/hashlib/keccak_test.py
tests/main/util/hashlib/ripemd_test.py
tests/main/util/hashlib/sha2_test.py
tests/main/util/hashlib/sha3_test.py
tests/main/util/signature/__init__.py
tests/main/util/signature/ed25519/__init__.py
tests/main/util/signature/ed25519/sha2_test.py
tests/main/util/signature/ed25519/sha3_test.py
tests/random/__init__.py
tests/random/randomize_test.py
tests/random/client/__init__.py
tests/random/models/__init__.py
tests/random/models/account_test.py
tests/random/models/blockchain_test.py
tests/random/models/mosaic_test.py
tests/random/util/__init__.py
tests/random/util/base64_test.py
tests/random/util/binascii_test.py
tests/random/util/hashlib_test.py
tests/random/util/signature_test.py
xpx_chain-0.6.6.dist-info/LICENSE
xpx_chain-0.6.6.dist-info/METADATA
xpx_chain-0.6.6.dist-info/WHEEL
xpx_chain-0.6.6.dist-info/top_level.txt
xpx_chain-0.6.6.dist-info/RECORD
